{
  "sections": {
    "163164196053b08870": {
      "type": "image-banner",
      "blocks": {
        "163164196053b08870-0": {
          "type": "heading",
          "settings": {
            "heading": "Image banner",
            "heading_size": "medium"
          }
        },
        "163164196053b08870-1": {
          "type": "text",
          "settings": {
            "text": "Give customers details about the banner image(s) or content on the template."
          }
        },
        "163164196053b08870-2": {
          "type": "buttons",
          "settings": {
            "button_label_1": "Button label",
            "button_link_1": "",
            "button_style_secondary_1": false,
            "button_label_2": "Button label",
            "button_link_2": "",
            "button_style_secondary_2": false
          }
        }
      },
      "block_order": [
        "163164196053b08870-0",
        "163164196053b08870-1",
        "163164196053b08870-2"
      ],
      "settings": {
        "image": "shopify:\/\/shop_images\/IMG_2108.JPG",
        "image_2": "shopify:\/\/shop_images\/176549129_306370394201876_6679660250778184483_n.jpg",
        "adapt_height_first_image": true,
        "desktop_text_box_position": "center",
        "show_text_box": true,
        "image_overlay_opacity": 0,
        "color_scheme": "background-1",
        "stack_images_on_mobile": true,
        "show_text_below": true
      }
    },
    "163123164198c6b12f": {
      "type": "homepage-collection",
      "settings": {
        "title": "",
        "collection": "frontpage",
        "products_to_show": 48,
        "show_view_all": false,
        "swipe_on_mobile": false,
        "image_ratio": "square",
        "show_secondary_image": true,
        "add_image_padding": false,
        "show_image_outline": true,
        "show_vendor": false,
        "show_rating": false
      }
    }
  },
  "order": [
    "163164196053b08870",
    "163123164198c6b12f"
  ]
}
